cubical/DefaultParset.cfg
cubical/__init__.py
cubical/flagging.py
cubical/main.py
cubical/param_db.py
cubical/solver.py
cubical/statistics.py
cubical/workers.py
cubical/bin/gocubical
cubical/bin/plot-gain-solutions
cubical/bin/plot-leakage-solutions
cubical/bin/print-cubical-stats
cubical/data_handler/MBTiggerSim.py
cubical/data_handler/TiggerSourceProvider.py
cubical/data_handler/__init__.py
cubical/data_handler/ms_data_handler.py
cubical/data_handler/ms_tile.py
cubical/data_handler/wisdom.py
cubical/database/__init__.py
cubical/database/blankcaltable.CASA.tgz
cubical/database/casa_db_adaptor.py
cubical/database/iface_database.py
cubical/database/parameter.py
cubical/database/pickled_db.py
cubical/degridder/DDFacetSim.py
cubical/degridder/DicoSourceProvider.py
cubical/degridder/FITSBeamInterpolator.py
cubical/degridder/__init__.py
cubical/degridder/geometry.py
cubical/kernels/__init__.py
cubical/kernels/chain.py
cubical/kernels/diag_complex.py
cubical/kernels/diag_phase_only.py
cubical/kernels/diag_robust.py
cubical/kernels/diagdiag_complex.py
cubical/kernels/f_slope.py
cubical/kernels/ff2_slope.py
cubical/kernels/full_W_complex.py
cubical/kernels/full_complex.py
cubical/kernels/generics.py
cubical/kernels/madmax.py
cubical/kernels/phase_only.py
cubical/kernels/rebinning.py
cubical/kernels/t_slope.py
cubical/kernels/tf_plane.py
cubical/machines/__init__.py
cubical/machines/abstract_machine.py
cubical/machines/complex_2x2_machine.py
cubical/machines/complex_W_2x2_machine.py
cubical/machines/ifr_gain_machine.py
cubical/machines/interval_gain_machine.py
cubical/machines/jones_chain_machine.py
cubical/machines/jones_chain_robust_machine.py
cubical/machines/machine_types.py
cubical/machines/parallactic_machine.py
cubical/machines/parameterised_machine.py
cubical/machines/phase_diag_machine.py
cubical/machines/pol_gain_machine.py
cubical/machines/slope_machine.py
cubical/madmax/__init__.py
cubical/madmax/flagger.py
cubical/madmax/plots.py
cubical/plots/__init__.py
cubical-1.6.4.dist-info/LICENSE.md
cubical-1.6.4.dist-info/METADATA
cubical-1.6.4.dist-info/WHEEL
cubical-1.6.4.dist-info/entry_points.txt
cubical-1.6.4.dist-info/top_level.txt
cubical-1.6.4.dist-info/RECORD
