Metadata-Version: 2.1
Name: cubical
Version: 1.6.4
Summary: Fast calibration implementation exploiting complex optimisation.
Home-page: https://github.com/ratt-ru/CubiCal
Author: Jonathan Kenyon
Author-email: jonosken@gmail.com
License: GNU GPL v3
Platform: UNKNOWN
Classifier: Development Status :: 5 - Production/Stable
Classifier: Intended Audience :: Science/Research
Classifier: License :: OSI Approved :: GNU General Public License v3 (GPLv3)
Classifier: Operating System :: POSIX :: Linux
Classifier: Programming Language :: Python
Classifier: Topic :: Scientific/Engineering :: Astronomy
Requires-Python: >=3.6
License-File: LICENSE.md
Requires-Dist: future
Requires-Dist: numpy
Requires-Dist: numba
Requires-Dist: python-casacore
Requires-Dist: sharedarray (>=3.2.1)
Requires-Dist: matplotlib
Requires-Dist: scipy
Requires-Dist: astro-tigger-lsm
Requires-Dist: six
Requires-Dist: astropy (>=3.0)
Requires-Dist: psutil
Provides-Extra: degridder-support
Requires-Dist: ddfacet (>=0.6.1) ; extra == 'degridder-support'
Requires-Dist: regions (<0.5) ; extra == 'degridder-support'
Requires-Dist: meqtrees-cattery (>=1.7.7) ; extra == 'degridder-support'
Provides-Extra: lsm-support
Requires-Dist: montblanc (>=0.6.4) ; extra == 'lsm-support'
